YuniteAPI
