Metadata-Version: 2.1
Name: YuniteAPI
Version: 1.0.2
Summary: A asynchronous python wrapper for the Yunite API
Home-page: https://github.com/SylteA/YuniteAPI
Author: SylteA
License: MIT
Keywords: wrapper,Yunite,api
Platform: UNKNOWN
Classifier: Development Status :: 5 - Production/Stable
Classifier: Intended Audience :: Developers
Classifier: Natural Language :: English
Classifier: Programming Language :: Python :: 3.7
Classifier: Topic :: Software Development :: Libraries :: Python Modules
Classifier: Topic :: Utilities
Requires-Python: >=3.7.5
